sayhelloworldcute/__init__.py
sayhelloworldcute/main.py
sayhelloworldcute-0.1.0.dist-info/METADATA
sayhelloworldcute-0.1.0.dist-info/WHEEL
sayhelloworldcute-0.1.0.dist-info/top_level.txt
sayhelloworldcute-0.1.0.dist-info/RECORD
